LICENSE.txt
MANIFEST.in
README.md
requirements.txt
setup.cfg
setup.py
httpstatuspuppet/__init__.py
httpstatuspuppet/common.py
httpstatuspuppet/entrypoint.py
httpstatuspuppet/helpers.py
httpstatuspuppet/server.py
httpstatuspuppet.egg-info/PKG-INFO
httpstatuspuppet.egg-info/SOURCES.txt
httpstatuspuppet.egg-info/dependency_links.txt
httpstatuspuppet.egg-info/requires.txt
httpstatuspuppet.egg-info/top_level.txt
httpstatuspuppet.egg-info/zip-safe
httpstatuspuppet/tests/__init__.py
httpstatuspuppet/tests/test_server.py