Metadata-Version: 1.0
Name: httpstatuspuppet
Version: 1.0.1
Summary: A HTTP server that will return a status code of your choice
Home-page: https://github.com/wtsi-hgi/http-status-puppet.git
Author: UNKNOWN
Author-email: UNKNOWN
License: MIT
Platform: UNKNOWN
